chibi_donkey/__init__.py
chibi_donkey/donkey.py
chibi_donkey-1.0.2.dist-info/COPYING
chibi_donkey-1.0.2.dist-info/METADATA
chibi_donkey-1.0.2.dist-info/WHEEL
chibi_donkey-1.0.2.dist-info/top_level.txt
chibi_donkey-1.0.2.dist-info/RECORD
