Metadata-Version: 2.1
Name: chibi_donkey
Version: 1.0.2
Summary: library for proccess the format double undescore
Home-page: https://github.com/dem4ply/chibi_donkey
Author: dem4ply
Author-email: 
Classifier: Environment :: Console
Classifier: Intended Audience :: Developers
Classifier: Programming Language :: Python
License-File: COPYING
